predibase_pql/__init__.py
predibase_pql/api.py
predibase_pql/pql.py
predibase_pql/version.py
predibase_pql/workflow.py
predibase_pql-0.7.12.dist-info/METADATA
predibase_pql-0.7.12.dist-info/WHEEL
predibase_pql-0.7.12.dist-info/top_level.txt
predibase_pql-0.7.12.dist-info/RECORD
